CHANGELOG.md
LICENSE
README.md
nv/tables/__init__.py
nv/tables/core.py
nv/tables/decorators.py
nv/tables/encoding.py
nv/tables/implementations/__init__.py
nv/tables/implementations/csv.py
nv/tables/implementations/xls.py
nv/tables/implementations/xlsx.py
nv/tables/normalization.py
nv/tables/spreadsheets.py
nv/tables/typing.py
nv_tables-0.1.2.dist-info/LICENSE
nv_tables-0.1.2.dist-info/WHEEL
nv_tables-0.1.2.dist-info/METADATA
nv_tables-0.1.2.dist-info/RECORD
