Metadata-Version: 2.1
Name: nv-tables
Version: 0.1.2
Summary: Tools for read and write data from and into table files (e.g. xls, xlsx, csv, etc.)
Home-page: https://github.com/gstos/nv-utils
License: MIT
Author: Gustavo Santos
Author-email: gustavo@next.ventures
Requires-Python: >=3.10,<4.0
Classifier: License :: OSI Approved :: MIT License
Classifier: Operating System :: OS Independent
Classifier: Programming Language :: Python :: 3
Classifier: Programming Language :: Python :: 3.10
Classifier: Topic :: Software Development :: Libraries :: Python Modules
Provides-Extra: all
Provides-Extra: detect
Provides-Extra: xls
Provides-Extra: xlsx
Requires-Dist: charset-normalizer (>=2.0.10,<3.0.0); extra == "detect" or extra == "all"
Requires-Dist: openpyxl (>=3.0.9,<4.0.0); extra == "xlsx" or extra == "all"
Requires-Dist: pytest (>=7.1.1,<8.0.0)
Requires-Dist: xlrd (>=2.0.1,<3.0.0); extra == "xls" or extra == "all"
Requires-Dist: xlutils (>=2.0.0,<3.0.0); extra == "xls" or extra == "all"
Requires-Dist: xlwt (>=1.3.0,<2.0.0); extra == "xls" or extra == "all"
Project-URL: Repository, https://github.com/gstos/nv-utils
